zoro_ds_utils/VERSION
zoro_ds_utils/__init__.py
zoro_ds_utils/general.py
zoro_ds_utils/profilers.py
zoro_ds_utils-0.0.1.dist-info/METADATA
zoro_ds_utils-0.0.1.dist-info/WHEEL
zoro_ds_utils-0.0.1.dist-info/entry_points.txt
zoro_ds_utils-0.0.1.dist-info/top_level.txt
zoro_ds_utils-0.0.1.dist-info/RECORD
